quick_torch/__init__.py
quick_torch/quickdraw.py
quick_torch/utils.py
quick_torch-1.0.4.dist-info/LICENSE
quick_torch-1.0.4.dist-info/METADATA
quick_torch-1.0.4.dist-info/WHEEL
quick_torch-1.0.4.dist-info/top_level.txt
quick_torch-1.0.4.dist-info/RECORD
