Metadata-Version: 2.1
Name: quick_torch
Version: 1.0.4
Summary: Library that provides a QuickDraw dataset using the Pytorch API.
Home-page: https://github.com/framunoz/quick-torch
Author: Francisco Muñoz G.
License: MIT
Classifier: Environment :: GPU :: NVIDIA CUDA :: 11.8
Classifier: Environment :: Console
Classifier: Intended Audience :: Developers
Classifier: Intended Audience :: Science/Research
Classifier: License :: OSI Approved :: MIT License
Classifier: Operating System :: OS Independent
Classifier: Programming Language :: Python
Classifier: Programming Language :: Python :: 3.10
Classifier: Programming Language :: Python :: 3.11
Classifier: Topic :: Scientific/Engineering :: Artificial Intelligence
Classifier: Topic :: Scientific/Engineering :: Image Processing
Classifier: Topic :: Scientific/Engineering :: Image Recognition
Classifier: Topic :: Scientific/Engineering :: Visualization
Requires-Python: >=3.10
License-File: LICENSE
Requires-Dist: setuptools
Requires-Dist: requests
Requires-Dist: torchvision
Requires-Dist: jsonlines
